Workbook

Sheet Data
C7: Name | E7: مصطفي محمود علي
C8: Phone Number | E8: 01032340302
C9: E-Mail | E9: shroh1520132020sh@gmail.com

Sheet Info
C4: اسم العمود | D4: وظيفة العمود
C5: Date | D5: تاريخ عملية البيع
C6: Customer_Age | D6: عمر العميل وقت عملية الشراء
C7: Customer_Gender | D7: نوع العميل
C8: Country | D8: الدولة التي تمت فيها عملية البيع
C9: State | D9: الولاية أو المنطقة داخل الدولة
C10: Sub_Category | D10: الفئة الفرعية للمنتج
C11: Bike_Color | D11: لون الدراجة
C12: Product | D12: اسم المنتج ومقاسه
C13: Order_Quantity | D13: عدد الوحدات التي تم بيعها في العملية
C14: Unit_Cost | D14: تكلفة الوحدة الواحدة على الشركة
C15: Unit_Price | D15: سعر بيع الوحدة الواحدة للعميل

Sheet Sales Data
A1: Date | B1: Customer_Age | C1: CustoMer_Gender | D1: Country | E1: State | F1: Sub_Category | G1: Bike_Color | H1: Product | I1: Order_Quantity | J1: Unit_Cost | K1: Unit_Price | L1: Sales_Amount | M1: Cost_Amount | N1: Profit | O1: Profit_Margin | P1: Year | Q1: Month | R1: Age_Band
A2: 44501 | B2: 17 | C2: M | D2: Australia | E2: Victoria | F2: Road Bikes | G2: Black | H2: Road-750 Black, 48 | I2: 3 | J2: 700 | K2: 1100 | L2: =I2*K2 | M2: =I2*J2 | N2: =L2-M2 | O2: =IFERROR(N2/L2,0) | P2: =YEAR(A2) | Q2: =TEXT(A2,"mmm") | R2: =IF(B2<25,"18-24",IF(B2<35,"25-34",IF(B2<45,"35-44","45+")))
A3: 44502 | B3: 17 | C3: M | D3: Australia | E3: New South Wales | F3: Road Bikes | G3: Red | H3: Road-650 Red, 48 | I3: 3 | J3: 620 | K3: 980 | L3: =I3*K3 | M3: =I3*J3 | N3: =L3-M3 | O3: =IFERROR(N3/L3,0) | P3: =YEAR(A3) | Q3: =TEXT(A3,"mmm") | R3: =IF(B3<25,"18-24",IF(B3<35,"25-34",IF(B3<45,"35-44","45+")))
A4: 44502 | B4: 17 | C4: M | D4: Australia | E4: Victoria | F4: Road Bikes | G4: Black | H4: Road-750 Black, 48 | I4: 3 | J4: 700 | K4: 1100 | L4: =I4*K4 | M4: =I4*J4 | N4: =L4-M4 | O4: =IFERROR(N4/L4,0) | P4: =YEAR(A4) | Q4: =TEXT(A4,"mmm") | R4: =IF(B4<25,"18-24",IF(B4<35,"25-34",IF(B4<45,"35-44","45+")))
A5: 44508 | B5: 17 | C5: M | D5: Australia | E5: New South Wales | F5: Road Bikes | G5: Red | H5: Road-650 Red, 48 | I5: 1 | J5: 620 | K5: 980 | L5: =I5*K5 | M5: =I5*J5 | N5: =L5-M5 | O5: =IFERROR(N5/L5,0) | P5: =YEAR(A5) | Q5: =TEXT(A5,"mmm") | R5: =IF(B5<25,"18-24",IF(B5<35,"25-34",IF(B5<45,"35-44","45+")))
A6: 44511 | B6: 17 | C6: M | D6: Australia | E6: Queensland | F6: Road Bikes | G6: Red | H6: Road-650 Red, 58 | I6: 4 | J6: 620 | K6: 980 | L6: =I6*K6 | M6: =I6*J6 | N6: =L6-M6 | O6: =IFERROR(N6/L6,0) | P6: =YEAR(A6) | Q6: =TEXT(A6,"mmm") | R6: =IF(B6<25,"18-24",IF(B6<35,"25-34",IF(B6<45,"35-44","45+")))
A7: 44518 | B7: 17 | C7: M | D7: Australia | E7: New South Wales | F7: Road Bikes | G7: Red | H7: Road-650 Red, 48 | I7: 2 | J7: 620 | K7: 980 | L7: =I7*K7 | M7: =I7*J7 | N7: =L7-M7 | O7: =IFERROR(N7/L7,0) | P7: =YEAR(A7) | Q7: =TEXT(A7,"mmm") | R7: =IF(B7<25,"18-24",IF(B7<35,"25-34",IF(B7<45,"35-44","45+")))
A8: 44518 | B8: 17 | C8: M | D8: Australia | E8: Queensland | F8: Road Bikes | G8: Red | H8: Road-650 Red, 58 | I8: 1 | J8: 620 | K8: 980 | L8: =I8*K8 | M8: =I8*J8 | N8: =L8-M8 | O8: =IFERROR(N8/L8,0) | P8: =YEAR(A8) | Q8: =TEXT(A8,"mmm") | R8: =IF(B8<25,"18-24",IF(B8<35,"25-34",IF(B8<45,"35-44","45+")))
A9: 44523 | B9: 17 | C9: M | D9: Australia | E9: New South Wales | F9: Road Bikes | G9: Red | H9: Road-650 Red, 48 | I9: 1 | J9: 620 | K9: 980 | L9: =I9*K9 | M9: =I9*J9 | N9: =L9-M9 | O9: =IFERROR(N9/L9,0) | P9: =YEAR(A9) | Q9: =TEXT(A9,"mmm") | R9: =IF(B9<25,"18-24",IF(B9<35,"25-34",IF(B9<45,"35-44","45+")))
A10: 44526 | B10: 17 | C10: F | D10: Australia | E10: New South Wales | F10: Road Bikes | G10: Red | H10: Road-650 Red, 58 | I10: 1 | J10: 620 | K10: 980 | L10: =I10*K10 | M10: =I10*J10 | N10: =L10-M10 | O10: =IFERROR(N10/L10,0) | P10: =YEAR(A10) | Q10: =TEXT(A10,"mmm") | R10: =IF(B10<25,"18-24",IF(B10<35,"25-34",IF(B10<45,"35-44","45+")))
A11: 44529 | B11: 17 | C11: F | D11: Australia | E11: Tasmania | F11: Road Bikes | G11: Black | H11: Road-750 Black, 48 | I11: 4 | J11: 700 | K11: 1100 | L11: =I11*K11 | M11: =I11*J11 | N11: =L11-M11 | O11: =IFERROR(N11/L11,0) | P11: =YEAR(A11) | Q11: =TEXT(A11,"mmm") | R11: =IF(B11<25,"18-24",IF(B11<35,"25-34",IF(B11<45,"35-44","45+")))
A12: 44529 | B12: 17 | C12: M | D12: France | E12: Nord | F12: Mountain Bikes | G12: Silver | H12: Mountain-200 Silver, 46 | I12: 1 | J12: 550 | K12: 850 | L12: =I12*K12 | M12: =I12*J12 | N12: =L12-M12 | O12: =IFERROR(N12/L12,0) | P12: =YEAR(A12) | Q12: =TEXT(A12,"mmm") | R12: =IF(B12<25,"18-24",IF(B12<35,"25-34",IF(B12<45,"35-44","45+")))
A13: 44530 | B13: 17 | C13: M | D13: Australia | E13: New South Wales | F13: Road Bikes | G13: Red | H13: Road-650 Red, 48 | I13: 3 | J13: 620 | K13: 980 | L13: =I13*K13 | M13: =I13*J13 | N13: =L13-M13 | O13: =IFERROR(N13/L13,0) | P13: =YEAR(A13) | Q13: =TEXT(A13,"mmm") | R13: =IF(B13<25,"18-24",IF(B13<35,"25-34",IF(B13<45,"35-44","45+")))
... A753: 44539 | B753: 75 | C753: M | D753: United Kingdom | E753: England | F753: Road Bikes | G753: Black | H753: Road-250 Black, 48 | I753: 2 | J753: 580 | K753: 920 | L753: =I753*K753 | M753: =I753*J753 | N753: =L753-M753 | O753: =IFERROR(N753/L753,0) | P753: =YEAR(A753) | Q753: =TEXT(A753,"mmm") | R753: =IF(B753<25,"18-24",IF(B753<35,"25-34",IF(B753<45,"35-44","45+")))

Sheet Analysis
A1: Task 1 | Excel Functions & Data Analysis
A3: Metric | B3: Formula / Result | C3: Use
A4: Records | B4: =COUNT('Sales Data'!A2:A753) | C4: COUNT
A5: Unique Products | B5: =COUNTA('Unique Lists'!A2:A753) | C5: COUNTA
A6: Blank Products | B6: =COUNTBLANK('Sales Data'!H2:H753) | C6: COUNTBLANK
A7: Total Sales | B7: =SUM('Sales Data'!L2:L753) | C7: SUM
A8: Average Sales/Row | B8: =AVERAGE('Sales Data'!L2:L753) | C8: AVERAGE
A9: Road Bikes Count | B9: =COUNTIF('Sales Data'!F2:F753,"Road Bikes") | C9: COUNTIF
A10: Road Bikes Sales | B10: =SUMIF('Sales Data'!F2:F753,"Road Bikes",'Sales Data'!L2:L753) | C10: SUMIF
A11: Road Bikes Avg Profit | B11: =AVERAGEIF('Sales Data'!F2:F753,"Road Bikes",'Sales Data'!N2:N753) | C11: AVERAGEIF
A14: COUNTIFS / SUMIFS / AVERAGEIFS
A15: Criteria: Road Bikes + Black | B15: Road Bikes | C15: Black
A16: COUNTIFS | B16: =COUNTIFS('Sales Data'!F2:F753,B15,'Sales Data'!G2:G753,C15)
A17: SUMIFS | B17: =SUMIFS('Sales Data'!L2:L753,'Sales Data'!F2:F753,B15,'Sales Data'!G2:G753,C15)
A18: AVERAGEIFS | B18: =AVERAGEIFS('Sales Data'!N2:N753,'Sales Data'!F2:F753,B15,'Sales Data'!G2:G753,C15)
A21: RANK Example
A22: First row profit rank | B22: =RANK.EQ('Sales Data'!N2,'Sales Data'!N2:N753,0)
A27: Sub_Category | B27: Count | C27: Total Sales | D27: Average Profit
A28: Mountain Bikes | B28: =COUNTIF('Sales Data'!F2:F753,A28) | C28: =SUMIF('Sales Data'!F2:F753,A28,'Sales Data'!L2:L753) | D28: =AVERAGEIF('Sales Data'!F2:F753,A28,'Sales Data'!N2:N753)
A29: Road Bikes | B29: =COUNTIF('Sales Data'!F2:F753,A29) | C29: =SUMIF('Sales Data'!F2:F753,A29,'Sales Data'!L2:L753) | D29: =AVERAGEIF('Sales Data'!F2:F753,A29,'Sales Data'!N2:N753)

Sheet Unique Lists
A1: Unique Products (UNIQUE) | C1: Explicit Unique List
A2: =UNIQUE('Sales Data'!H2:H753) | C2: Mountain-100 Black, 38
C3: Mountain-100 Black, 42
C4: Mountain-100 Black, 48
C5: Mountain-100 Silver, 44
C6: Mountain-200 Black, 38
C7: Mountain-200 Black, 42
C8: Mountain-200 Black, 46
C9: Mountain-200 Silver, 38
C10: Mountain-200 Silver, 42
C11: Mountain-200 Silver, 46
C12: Mountain-400-W Silver, 38
C13: Mountain-400-W Silver, 40
C14: Mountain-400-W Silver, 42
... C61: Road-750 Black, 58

Sheet README
A1: Task 1 | Excel for Data Analytics
A3: مصدر البيانات | B3: تم استخدام ورقة Sales Data من Bike_Sales.xlsx لأن Task 1 لم يحتوي على مرفق مستقل ظاهر في Classroom.
A4: الأعمدة الجديدة | B4: Sales_Amount = Order_Quantity × Unit_Price، Cost_Amount = Order_Quantity × Unit_Cost، Profit، Profit_Margin، Year، Month، Age_Band.
A5: سبب الإضافة | B5: تسهيل حساب إجمالي المبيعات والتكلفة والربح والهامش، وتجميع الأداء زمنيًا وعمريًا.
A6: الدوال | B6: COUNT, COUNTIF, COUNTIFS, COUNTA, COUNTBLANK, SUM, SUMIF, SUMIFS, AVERAGE, AVERAGEIF, AVERAGEIFS, RANK.EQ, UNIQUE.
A7: Tables & Ranges | B7: تم تحويل Sales Data إلى Excel Table باسم BikeSalesData مع فلاتر وتنسيق منظم.
A8: Conditional Formatting | B8: تم تطبيق Color Scale على المبيعات والربح والهامش وData Bar على ملخص Sub_Category.
A9: المخرجات | B9: Analysis للإجابات والمؤشرات، Unique Lists لتطبيق UNIQUE، وREADME لشرح خطوات العمل.
